s5_interfaces/53_reset/rst_sim/reset_hist/counter_hist_RAM_AUTO_1R1W_rom.v
// ==============================================================
// Generated by Vitis HLS v2023.2.2
// Copyright 1986-2022 Xilinx, Inc. All Rights Reserved.
// Copyright 2022-2024 Advanced Micro Devices, Inc. All Rights Reserved.
// ==============================================================
`timescale 1 ns / 1 ps
module counter_hist_RAM_AUTO_1R1W_rom (
    address0, ce0, q0, 
    reset, clk);

parameter DataWidth = 8;
parameter AddressWidth = 3;
parameter AddressRange = 8;
 
input[AddressWidth-1:0] address0;
input ce0;
output reg[DataWidth-1:0] q0;

input reset;
input clk;

 
reg [DataWidth-1:0] rom0[0:AddressRange-1];


initial begin
     
    $readmemh("./counter_hist_RAM_AUTO_1R1W_rom.dat", rom0);
end

  
always @(posedge clk) 
begin 
    if (ce0) 
    begin
        q0 <= rom0[address0];
    end
end


endmodule

s5_interfaces/53_reset/rst_sim/reset_hist/counter_hist_RAM_AUTO_1R1W_ram.v
// ==============================================================
// Generated by Vitis HLS v2023.2.2
// Copyright 1986-2022 Xilinx, Inc. All Rights Reserved.
// Copyright 2022-2024 Advanced Micro Devices, Inc. All Rights Reserved.
// ==============================================================
`timescale 1 ns / 1 ps
module counter_hist_RAM_AUTO_1R1W_ram (
     
    address0, ce0,
    d0, we0, 
    q0, 
     
    reset, clk);

parameter DataWidth = 8;
parameter AddressWidth = 3;
parameter AddressRange = 8;
 
input[AddressWidth-1:0] address0;
input ce0;
input[DataWidth-1:0] d0;
input we0; 
output reg[DataWidth-1:0] q0; 

input reset;
input clk;

(* ram_style = "auto"  *)reg [DataWidth-1:0] ram[0:AddressRange-1];


 





//read first
always @(posedge clk)  
begin 
    if (ce0) begin
        if (we0) 
            ram[address0] <= d0; 
        q0 <= ram[address0];

    end
end 
 
 

endmodule

s5_interfaces/53_reset/rst_sim/reset_hist/counter_hist_RAM_AUTO_1R1W.v
// ==============================================================
// Generated by Vitis HLS v2023.2.2
// Copyright 1986-2022 Xilinx, Inc. All Rights Reserved.
// Copyright 2022-2024 Advanced Micro Devices, Inc. All Rights Reserved.
// ==============================================================

`timescale 1ns/1ps

module counter_hist_RAM_AUTO_1R1W
#(parameter
    DataWidth    = 8,
    AddressWidth = 3,
    AddressRange = 8
)(
    input  wire [AddressWidth-1:0] address0,
    input  wire                    ce0,
    input  wire                    we0,
    input  wire [DataWidth-1:0]    d0,
    output wire [DataWidth-1:0]    q0,
    input  wire                    clk,
    input  wire                    reset
);
//------------------------Local signal-------------------
reg  [AddressRange-1:0] written = {AddressRange{1'b0}} ;
wire [DataWidth-1:0]    q0_ram;
wire [DataWidth-1:0]    q0_rom;
wire                    q0_sel;
reg  [0:0]              sel0_sr;

//------------------------Instantiation------------------
counter_hist_RAM_AUTO_1R1W_ram #(
    .DataWidth(DataWidth),
    .AddressWidth(AddressWidth),
    .AddressRange(AddressRange))
counter_hist_RAM_AUTO_1R1W_ram_u(
    .address0       ( address0 ),
    .ce0            ( ce0 ),
    .we0            ( we0 ),
    .d0             ( d0 ),
    .q0             ( q0_ram ),
    .clk                ( clk ),
    .reset              ( reset )
);
counter_hist_RAM_AUTO_1R1W_rom #(
    .DataWidth(DataWidth),
    .AddressWidth(AddressWidth),
    .AddressRange(AddressRange))
counter_hist_RAM_AUTO_1R1W_rom_u(
    .ce0      ( ce0 ),
    .address0 ( address0 ),
    .q0       ( q0_rom ),
    .clk          ( clk ),
    .reset        ( reset )
);
//------------------------Body---------------------------
assign q0     = q0_sel? q0_ram : q0_rom;
assign q0_sel = sel0_sr[0];


always @(posedge clk ) begin
    if (reset)
        written <= 1'b0;
    else begin
        if (ce0 & we0) begin
            written[address0] <= 1'b1;
        end
    end
end

always @(posedge clk) begin
    if (ce0) begin
        sel0_sr[0] <= written[address0];
    end
end

endmodule

s5_interfaces/53_reset/rst_sim/reset_hist/counter.v
// ==============================================================
// Generated by Vitis HLS v2023.2.2
// Copyright 1986-2022 Xilinx, Inc. All Rights Reserved.
// Copyright 2022-2024 Advanced Micro Devices, Inc. All Rights Reserved.
// ==============================================================

`timescale 1 ns / 1 ps 

(* CORE_GENERATION_INFO="counter_counter,hls_ip_2023_2_2,{HLS_INPUT_TYPE=cxx,HLS_INPUT_FLOAT=0,HLS_INPUT_FIXED=0,HLS_INPUT_PART=xcku5p-ffvb676-2-e,HLS_INPUT_CLOCK=3.330000,HLS_INPUT_ARCH=others,HLS_SYN_CLOCK=2.119000,HLS_SYN_LAT=1,HLS_SYN_TPT=none,HLS_SYN_MEM=0,HLS_SYN_DSP=0,HLS_SYN_FF=29,HLS_SYN_LUT=67,HLS_VERSION=2023_2_2}" *)

module counter (
        ap_clk,
        ap_rst,
        ap_start,
        ap_done,
        ap_idle,
        ap_ready,
        slot,
        hits,
        hits_ap_vld,
        ap_return
);

parameter    ap_ST_fsm_state1 = 2'd1;
parameter    ap_ST_fsm_state2 = 2'd2;

input   ap_clk;
input   ap_rst;
input   ap_start;
output   ap_done;
output   ap_idle;
output   ap_ready;
input  [2:0] slot;
output  [7:0] hits;
output   hits_ap_vld;
output  [7:0] ap_return;

reg ap_done;
reg ap_idle;
reg ap_ready;
reg hits_ap_vld;

(* fsm_encoding = "none" *) reg   [1:0] ap_CS_fsm;
wire    ap_CS_fsm_state1;
reg   [7:0] cnt;
reg   [2:0] hist_address0;
reg    hist_ce0;
reg    hist_we0;
wire   [7:0] hist_q0;
reg   [2:0] hist_addr_reg_93;
wire   [63:0] zext_ln12_fu_64_p1;
wire   [7:0] add_ln11_fu_73_p2;
wire    ap_CS_fsm_state2;
wire   [7:0] h_fu_85_p2;
reg   [1:0] ap_NS_fsm;
reg    ap_ST_fsm_state1_blk;
wire    ap_ST_fsm_state2_blk;
wire    ap_ce_reg;

// power-on initialization
initial begin
#0 ap_CS_fsm = 2'd1;
#0 cnt = 8'd100;
end

counter_hist_RAM_AUTO_1R1W #(
    .DataWidth( 8 ),
    .AddressRange( 8 ),
    .AddressWidth( 3 ))
hist_U(
    .clk(ap_clk),
    .reset(ap_rst),
    .address0(hist_address0),
    .ce0(hist_ce0),
    .we0(hist_we0),
    .d0(h_fu_85_p2),
    .q0(hist_q0)
);

always @ (posedge ap_clk) begin
    if (ap_rst == 1'b1) begin
        ap_CS_fsm <= ap_ST_fsm_state1;
    end else begin
        ap_CS_fsm <= ap_NS_fsm;
    end
end

always @ (posedge ap_clk) begin
    if ((1'b1 == ap_CS_fsm_state2)) begin
        cnt <= add_ln11_fu_73_p2;
    end
end

always @ (posedge ap_clk) begin
    if ((1'b1 == ap_CS_fsm_state1)) begin
        hist_addr_reg_93 <= zext_ln12_fu_64_p1;
    end
end

always @ (*) begin
    if ((ap_start == 1'b0)) begin
        ap_ST_fsm_state1_blk = 1'b1;
    end else begin
        ap_ST_fsm_state1_blk = 1'b0;
    end
end

assign ap_ST_fsm_state2_blk = 1'b0;

always @ (*) begin
    if ((1'b1 == ap_CS_fsm_state2)) begin
        ap_done = 1'b1;
    end else begin
        ap_done = 1'b0;
    end
end

always @ (*) begin
    if (((ap_start == 1'b0) & (1'b1 == ap_CS_fsm_state1))) begin
        ap_idle = 1'b1;
    end else begin
        ap_idle = 1'b0;
    end
end

always @ (*) begin
    if ((1'b1 == ap_CS_fsm_state2)) begin
        ap_ready = 1'b1;
    end else begin
        ap_ready = 1'b0;
    end
end

always @ (*) begin
    if ((1'b1 == ap_CS_fsm_state2)) begin
        hist_address0 = hist_addr_reg_93;
    end else if ((1'b1 == ap_CS_fsm_state1)) begin
        hist_address0 = zext_ln12_fu_64_p1;
    end else begin
        hist_address0 = 'bx;
    end
end

always @ (*) begin
    if (((1'b1 == ap_CS_fsm_state2) | ((ap_start == 1'b1) & (1'b1 == ap_CS_fsm_state1)))) begin
        hist_ce0 = 1'b1;
    end else begin
        hist_ce0 = 1'b0;
    end
end

always @ (*) begin
    if ((1'b1 == ap_CS_fsm_state2)) begin
        hist_we0 = 1'b1;
    end else begin
        hist_we0 = 1'b0;
    end
end

always @ (*) begin
    if ((1'b1 == ap_CS_fsm_state2)) begin
        hits_ap_vld = 1'b1;
    end else begin
        hits_ap_vld = 1'b0;
    end
end

always @ (*) begin
    case (ap_CS_fsm)
        ap_ST_fsm_state1 : begin
            if (((ap_start == 1'b1) & (1'b1 == ap_CS_fsm_state1))) begin
                ap_NS_fsm = ap_ST_fsm_state2;
            end else begin
                ap_NS_fsm = ap_ST_fsm_state1;
            end
        end
        ap_ST_fsm_state2 : begin
            ap_NS_fsm = ap_ST_fsm_state1;
        end
        default : begin
            ap_NS_fsm = 'bx;
        end
    endcase
end

assign add_ln11_fu_73_p2 = (cnt + 8'd1);

assign ap_CS_fsm_state1 = ap_CS_fsm[32'd0];

assign ap_CS_fsm_state2 = ap_CS_fsm[32'd1];

assign ap_return = (cnt + 8'd1);

assign h_fu_85_p2 = (hist_q0 + 8'd1);

assign hits = h_fu_85_p2;

assign zext_ln12_fu_64_p1 = slot;

endmodule //counter

s5_interfaces/53_reset/tb/rst_tb.v
`timescale 1ns/1ps
// Lesson 5.3: drives ap_rst in the middle of a run, which co-simulation
// cannot do. Three calls, a two-cycle reset, three more calls, all on slot 0.
// Prints one line per call and writes rst_tb.vcd for a waveform viewer.
module rst_tb;
  reg        ap_clk = 1'b0, ap_rst = 1'b1, ap_start = 1'b0;
  reg  [2:0] slot = 3'd0;
  wire       ap_done, ap_idle, ap_ready, hits_ap_vld;
  wire [7:0] hits, ap_return;
  integer    cyc = 0;

  counter dut (.ap_clk(ap_clk), .ap_rst(ap_rst), .ap_start(ap_start),
               .ap_done(ap_done), .ap_idle(ap_idle), .ap_ready(ap_ready),
               .slot(slot), .hits(hits), .hits_ap_vld(hits_ap_vld),
               .ap_return(ap_return));

  always #1.665 ap_clk = ~ap_clk;            // 3.33 ns
  always @(posedge ap_clk) cyc <= cyc + 1;

  // Inputs change and outputs are sampled on falling edges, away from the
  // rising edges where the RTL registers update.
  task call(input integer n);
    integer lat, r, h, done;
    begin
      @(negedge ap_clk); ap_start = 1'b1; lat = 0; done = 0; h = -1;
      while (!done) begin
        @(negedge ap_clk); lat = lat + 1;
        if (hits_ap_vld) h = hits;
        if (ap_done) begin r = ap_return; done = 1; end
      end
      ap_start = 1'b0;
      $display("call %0d  cycle %0d  total %0d  hits %0d  start-to-done %0d",
               n, cyc, r, h, lat);
    end
  endtask

  task pulse_reset(input integer n);
    begin
      @(negedge ap_clk); ap_rst = 1'b1;
      repeat (n) @(negedge ap_clk);
      ap_rst = 1'b0;
    end
  endtask

  initial begin
    $dumpfile("rst_tb.vcd");
    $dumpvars(0, rst_tb);
    repeat (2) @(negedge ap_clk);            // time-zero reset, as in cosim
    ap_rst = 1'b0;
    call(1); call(2); call(3);
    $display("-- reset --");
    pulse_reset(2);
    call(4); call(5); call(6);
    $finish;
  end
endmodule

s5_interfaces/53_reset/rst_sim/reset_hist/rst_tb.vcd
$date
   Mon Sep 21 13:48:33 2026
$end

$version
  2023.2.2
  $dumpfile ("rst_tb.vcd") 
$end

$timescale
  1ps
$end

$scope module rst_tb $end
$var reg 1 ! ap_clk $end
$var reg 1 " ap_rst $end
$var reg 1 # ap_start $end
$var reg 3 $ slot [2:0] $end
$var wire 1 % ap_done $end
$var wire 1 & ap_idle $end
$var wire 1 ' ap_ready $end
$var wire 1 ( hits_ap_vld $end
$var wire 8 ) hits [7:0] $end
$var wire 8 * ap_return [7:0] $end
$var integer 32 + cyc [31:0] $end
$scope module dut $end
$var wire 1 , ap_clk $end
$var wire 1 - ap_rst $end
$var wire 1 . ap_start $end
$var wire 3 / slot [2:0] $end
$var wire 8 ) hits [7:0] $end
$var wire 8 * ap_return [7:0] $end
$var reg 1 0 ap_done $end
$var reg 1 1 ap_idle $end
$var reg 1 2 ap_ready $end
$var reg 1 3 hits_ap_vld $end
$var reg 2 4 ap_CS_fsm [1:0] $end
$var wire 1 5 ap_CS_fsm_state1 $end
$var reg 8 6 cnt [7:0] $end
$var reg 3 7 hist_address0 [2:0] $end
$var reg 1 8 hist_ce0 $end
$var reg 1 9 hist_we0 $end
$var wire 8 : hist_q0 [7:0] $end
$var reg 3 ; hist_addr_reg_93 [2:0] $end
$var wire 64 < zext_ln12_fu_64_p1 [63:0] $end
$var wire 8 = add_ln11_fu_73_p2 [7:0] $end
$var wire 1 > ap_CS_fsm_state2 $end
$var wire 8 ? h_fu_85_p2 [7:0] $end
$var reg 2 @ ap_NS_fsm [1:0] $end
$var reg 1 A ap_ST_fsm_state1_blk $end
$var wire 1 B ap_ST_fsm_state2_blk $end
$var wire 1 C ap_ce_reg $end
$scope module hist_U $end
$var wire 3 D address0 [2:0] $end
$var wire 1 E ce0 $end
$var wire 1 F we0 $end
$var wire 8 ? d0 [7:0] $end
$var wire 8 : q0 [7:0] $end
$var wire 1 , clk $end
$var wire 1 - reset $end
$var reg 8 G written [7:0] $end
$var wire 8 H q0_ram [7:0] $end
$var wire 8 I q0_rom [7:0] $end
$var wire 1 J q0_sel $end
$var reg 1 K sel0_sr [0:0] $end
$scope module counter_hist_RAM_AUTO_1R1W_ram_u $end
$var wire 3 D address0 [2:0] $end
$var wire 1 E ce0 $end
$var wire 8 ? d0 [7:0] $end
$var wire 1 F we0 $end
$var reg 8 L q0 [7:0] $end
$var wire 1 - reset $end
$var wire 1 , clk $end
$upscope $end
$scope module counter_hist_RAM_AUTO_1R1W_rom_u $end
$var wire 3 D address0 [2:0] $end
$var wire 1 E ce0 $end
$var reg 8 M q0 [7:0] $end
$var wire 1 - reset $end
$var wire 1 , clk $end
$upscope $end
$upscope $end
$upscope $end
$scope task call $end
$var integer 32 N n [31:0] $end
$var integer 32 O lat [31:0] $end
$var integer 32 P r [31:0] $end
$var integer 32 Q h [31:0] $end
$var integer 32 R done [31:0] $end
$upscope $end
$scope task pulse_reset $end
$var integer 32 S n [31:0] $end
$upscope $end
$upscope $end
$enddefinitions $end

#0
$dumpvars
0!
1"
0#
b0 $
0%
1&
0'
0(
bx )
b1100101 *
b0 +
0,
1-
0.
b0 /
00
11
02
03
b1 4
15
b1100100 6
b0 7
08
09
bx :
bx ;
b0 <
b1100101 =
0>
bx ?
b1 @
1A
0B
zC
b0 D
0E
0F
b0 G
bx H
bx I
xJ
xK
bx L
bx M
bx N
bx O
bx P
bx Q
bx R
bx S
$end

#1665
1!
b1 +
1,
b0 ;

#3330
0!
0,

#4995
1!
b10 +
1,

#6660
0!
0"
0,
0-
b1 N

#8325
1!
b11 +
1,

#9990
0!
1#
0&
0,
1.
01
18
b10 @
0A
1E
b0 O
b11111111111111111111111111111111 Q
b0 R

#11655
1!
1%
1'
1(
b10 )
b100 +
1,
10
12
13
b10 4
05
19
b1 :
1>
b10 ?
b1 @
1F
b1 I
0J
0K
b1 M

#13320
0!
0#
0,
0.
1A
b10 N
b1 O
b1100101 P
b10 Q
b1 R

#14985
1!
0%
1&
0'
0(
b1100110 *
b101 +
1,
00
11
02
03
b1 4
15
b1100101 6
08
09
b1100110 =
0>
0E
0F
b1 G

#16650
0!
1#
0&
0,
1.
01
18
b10 @
0A
1E
b0 O
b11111111111111111111111111111111 Q
b0 R

#18315
1!
1%
1'
1(
b11 )
b110 +
1,
10
12
13
b10 4
05
19
b10 :
1>
b11 ?
b1 @
1F
b10 H
1J
1K
b10 L

#19980
0!
0#
0,
0.
1A
b11 N
b1 O
b1100110 P
b11 Q
b1 R

#21645
1!
0%
1&
0'
0(
b1100111 *
b111 +
1,
00
11
02
03
b1 4
15
b1100110 6
08
09
b1100111 =
0>
0E
0F

#23310
0!
1#
0&
0,
1.
01
18
b10 @
0A
1E
b0 O
b11111111111111111111111111111111 Q
b0 R

#24975
1!
1%
1'
1(
b100 )
b1000 +
1,
10
12
13
b10 4
05
19
b11 :
1>
b100 ?
b1 @
1F
b11 H
b11 L

#26640
0!
0#
0,
0.
1A
b1 O
b1100111 P
b100 Q
b1 R
b10 S

#28305
1!
0%
1&
0'
0(
b1101000 *
b1001 +
1,
00
11
02
03
b1 4
15
b1100111 6
08
09
b1101000 =
0>
0E
0F

#29970
0!
1"
0,
1-

#31635
1!
b1010 +
1,
b0 G

#33300
0!
0,

#34965
1!
b1011 +
1,

#36630
0!
0"
0,
0-
b100 N

#38295
1!
b1100 +
1,

#39960
0!
1#
0&
0,
1.
01
18
b10 @
0A
1E
b0 O
b11111111111111111111111111111111 Q
b0 R

#41625
1!
1%
1'
1(
b10 )
b1101 +
1,
10
12
13
b10 4
05
19
b1 :
1>
b10 ?
b1 @
1F
b100 H
0J
0K
b100 L

#43290
0!
0#
0,
0.
1A
b101 N
b1 O
b1101000 P
b10 Q
b1 R

#44955
1!
0%
1&
0'
0(
b1101001 *
b1110 +
1,
00
11
02
03
b1 4
15
b1101000 6
08
09
b1101001 =
0>
0E
0F
b1 G

#46620
0!
1#
0&
0,
1.
01
18
b10 @
0A
1E
b0 O
b11111111111111111111111111111111 Q
b0 R

#48285
1!
1%
1'
1(
b11 )
b1111 +
1,
10
12
13
b10 4
05
19
b10 :
1>
b11 ?
b1 @
1F
b10 H
1J
1K
b10 L

#49950
0!
0#
0,
0.
1A
b110 N
b1 O
b1101001 P
b11 Q
b1 R

#51615
1!
0%
1&
0'
0(
b1101010 *
b10000 +
1,
00
11
02
03
b1 4
15
b1101001 6
08
09
b1101010 =
0>
0E
0F

#53280
0!
1#
0&
0,
1.
01
18
b10 @
0A
1E
b0 O
b11111111111111111111111111111111 Q
b0 R

#54945
1!
1%
1'
1(
b100 )
b10001 +
1,
10
12
13
b10 4
05
19
b11 :
1>
b100 ?
b1 @
1F
b11 H
b11 L

#56610
0!
0#
0,
b1 O
b1101010 P
b100 Q
b1 R
